ploomber_scaffold/__init__.py
ploomber_scaffold/exceptions.py
ploomber_scaffold/scaffold.py
ploomber_scaffold/empty/no-package.yaml
ploomber_scaffold/empty/package.yaml
ploomber_scaffold/simple/pipeline.yaml
ploomber_scaffold/template/.gitattributes
ploomber_scaffold/template/.gitignore
ploomber_scaffold/template/MANIFEST.in
ploomber_scaffold/template/README.md
ploomber_scaffold/template/environment.dev.yml
ploomber_scaffold/template/environment.yml
ploomber_scaffold/template/requirements.dev.txt
ploomber_scaffold/template/requirements.txt
ploomber_scaffold/template/setup.cfg
ploomber_scaffold/template/setup.py
ploomber_scaffold/template/versioneer.py
ploomber_scaffold/template/exploratory/example.ipynb
ploomber_scaffold/template/products/.gitkeep
ploomber_scaffold/template/src/package_name/__init__.py
ploomber_scaffold/template/src/package_name/_version.py
ploomber_scaffold/template/src/package_name/pipeline.yaml
ploomber_scaffold/template/src/package_name/scripts/fit.py
ploomber_scaffold/template/src/package_name/tasks/__init__.py
ploomber_scaffold/template/src/package_name/tasks/features.py
ploomber_scaffold/template/src/package_name/tasks/raw.py
ploomber_scaffold/template/tests/test_exploratory.py
ploomber_scaffold/template/tests/test_pipeline.py
ploomber_scaffold-0.3.1.dist-info/LICENSE
ploomber_scaffold-0.3.1.dist-info/METADATA
ploomber_scaffold-0.3.1.dist-info/WHEEL
ploomber_scaffold-0.3.1.dist-info/top_level.txt
ploomber_scaffold-0.3.1.dist-info/RECORD
