Metadata-Version: 2.1
Name: ploomber-scaffold
Version: 0.3.1
Summary: UNKNOWN
Home-page: https://github.com/ploomber/scaffold
License: UNKNOWN
Platform: UNKNOWN
Classifier: Development Status :: 5 - Production/Stable
Classifier: Intended Audience :: Developers
Classifier: Intended Audience :: Science/Research
Classifier: License :: OSI Approved :: Apache Software License
Classifier: Operating System :: MacOS :: MacOS X
Classifier: Operating System :: Unix
Classifier: Operating System :: POSIX
Classifier: Operating System :: Microsoft :: Windows
Classifier: Programming Language :: Python
Classifier: Programming Language :: Python :: 3
Classifier: Programming Language :: Python :: 3.6
Classifier: Programming Language :: Python :: 3.7
Classifier: Programming Language :: Python :: 3.8
License-File: LICENSE
Requires-Dist: jinja2
Provides-Extra: dev
Requires-Dist: ploomber ; extra == 'dev'
Requires-Dist: pkgmt ; extra == 'dev'
Requires-Dist: twine ; extra == 'dev'
Requires-Dist: flake8 ; extra == 'dev'
Requires-Dist: yapf ; extra == 'dev'
Requires-Dist: pytest ; extra == 'dev'
Requires-Dist: invoke ; extra == 'dev'
Requires-Dist: ipython ; extra == 'dev'
Requires-Dist: nox ; extra == 'dev'
Requires-Dist: jedi (==0.17.2) ; extra == 'dev'
Requires-Dist: wheel ; extra == 'dev'
Requires-Dist: importlib-resources ; (python_version < "3.7") and extra == 'dev'
